lets_go/__init__.py
lets_go/backend.py
lets_go/board.py
lets_go/lets_go.py
lets_go-0.3.11.dist-info/METADATA
lets_go-0.3.11.dist-info/WHEEL
lets_go-0.3.11.dist-info/entry_points.txt
lets_go-0.3.11.dist-info/licenses/LICENSE
lets_go-0.3.11.dist-info/RECORD
