Metadata-Version: 2.1
Name: lets-go
Version: 0.3.11
Summary: A simple Go game in terminal environment
Project-URL: Homepage, https://github.com/brookssu/lets-go
Author-email: Brooks Su <yipeng00@gmail.com>
License:                                  Apache License
License-File: LICENSE
Keywords: alphago,game,go,ltermio,terminal,weiqi
Classifier: Development Status :: 2 - Pre-Alpha
Classifier: Environment :: Console
Classifier: Intended Audience :: End Users/Desktop
Classifier: License :: OSI Approved :: Apache Software License
Classifier: Natural Language :: English
Classifier: Operating System :: MacOS :: MacOS X
Classifier: Operating System :: POSIX
Classifier: Operating System :: Unix
Classifier: Programming Language :: Python :: 3.9
Classifier: Programming Language :: Python :: 3.10
Classifier: Programming Language :: Python :: 3.11
Classifier: Topic :: Games/Entertainment
Classifier: Topic :: Games/Entertainment :: Board Games
Requires-Python: >=3.7
Requires-Dist: ltermio>=0.6.3
